ults-0.1.0.dist-info/METADATA
ults-0.1.0.dist-info/WHEEL
ults-0.1.0.dist-info/licenses/LICENSE
ults/__init__.py
ults/functional.py
ults/ults.py
ults-0.1.0.dist-info/RECORD
