Metadata-Version: 2.1
Name: ults
Version: 0.1.0
Summary: Uncertainty-Guided Likelihood-Tree Search
Author: Julia Grosse, Agustinus Kristiadi
License: MIT
Classifier: Development Status :: 3 - Alpha
Classifier: License :: OSI Approved :: MIT License
Classifier: Operating System :: OS Independent
Classifier: Programming Language :: Python :: 3.9
Requires-Python: >=3.9
Requires-Dist: datasets
Requires-Dist: networkx
Requires-Dist: tokenizers
Requires-Dist: torch>=2.0
Requires-Dist: transformers
